nalogo/__init__.py
nalogo/_http.py
nalogo/auth.py
nalogo/client.py
nalogo/exceptions.py
nalogo/income.py
nalogo/payment_type.py
nalogo/receipt.py
nalogo/tax.py
nalogo/user.py
nalogo/dto/__init__.py
nalogo/dto/device.py
nalogo/dto/income.py
nalogo/dto/invoice.py
nalogo/dto/payment_type.py
nalogo/dto/tax.py
nalogo/dto/user.py
nalogo-1.0.0.dist-info/licenses/LICENSE
nalogo-1.0.0.dist-info/METADATA
nalogo-1.0.0.dist-info/WHEEL
nalogo-1.0.0.dist-info/top_level.txt
nalogo-1.0.0.dist-info/RECORD
