Metadata-Version: 2.4
Name: nalogo
Version: 1.0.0
Summary: Asynchronous Python client for Russian self-employed tax service API (Moy Nalog / lknpd.nalog.ru)
Author-email: NaloGO Contributors <contributors@nalogo.com>
License: MIT
Project-URL: Homepage, https://github.com/your-org/nalogo
Project-URL: Documentation, https://github.com/your-org/nalogo#readme
Project-URL: Repository, https://github.com/your-org/nalogo
Project-URL: Bug Reports, https://github.com/your-org/nalogo/issues
Project-URL: Changelog, https://github.com/your-org/nalogo/blob/main/CHANGELOG.md
Project-URL: Original PHP Library, https://github.com/shoman4eg/moy-nalog
Keywords: nalog,tax,self-employed,api,async,russia,moy-nalog,freelancer,invoice,receipt,lknpd,самозанятый
Classifier: Development Status :: 4 - Beta
Classifier: Intended Audience :: Developers
Classifier: License :: OSI Approved :: MIT License
Classifier: Operating System :: OS Independent
Classifier: Programming Language :: Python :: 3
Classifier: Programming Language :: Python :: 3.11
Classifier: Programming Language :: Python :: 3.12
Classifier: Programming Language :: Python :: 3 :: Only
Classifier: Topic :: Internet :: WWW/HTTP :: HTTP Servers
Classifier: Topic :: Software Development :: Libraries :: Python Modules
Classifier: Topic :: Office/Business :: Financial :: Accounting
Classifier: Topic :: Internet :: WWW/HTTP :: Dynamic Content
Classifier: Typing :: Typed
Classifier: Framework :: AsyncIO
Classifier: Framework :: Pydantic
Requires-Python: >=3.11
License-File: LICENSE
Requires-Dist: httpx>=0.25.0
Requires-Dist: pydantic<3.0.0,>=2.0.0
Requires-Dist: python-dotenv>=1.0.0
Provides-Extra: dev
Requires-Dist: pytest>=7.0.0; extra == "dev"
Requires-Dist: pytest-asyncio>=0.21.0; extra == "dev"
Requires-Dist: pytest-cov>=4.0.0; extra == "dev"
Requires-Dist: respx>=0.20.0; extra == "dev"
Requires-Dist: ruff>=0.1.0; extra == "dev"
Requires-Dist: black>=23.0.0; extra == "dev"
Requires-Dist: mypy>=1.0.0; extra == "dev"
Requires-Dist: coverage>=7.0.0; extra == "dev"
Requires-Dist: bandit[toml]>=1.7.0; extra == "dev"
Requires-Dist: build>=1.0.0; extra == "dev"
Requires-Dist: twine>=4.0.0; extra == "dev"
Dynamic: license-file
